{
    "task": 12,
    "location": "I.1",

    "solver": "CMTV",

    "refs":
    [
        {
            "title": "Фихтегольц Г.М. Курс дифференциального и интегрального исчисления. Том I",
            "desc": "Для успешного решения настоятельно рекомендую пройти §2 (Введение иррациональных чисел...), где подробно описывается метод сечений и зачем он нужен, так как в самом задачнике про сечения написано очень поверхностно."
        },
        {
            "title": "Задача 11",
            "desc": "Почти аналогичная задача, только попроще. Алгоритм решения абсолютно такой же",
            "link": "/tasks/11/"
        }
    ]
}